README.rst
ftree.py
setup.py
ftree.egg-info/PKG-INFO
ftree.egg-info/SOURCES.txt
ftree.egg-info/dependency_links.txt
ftree.egg-info/top_level.txt