Metadata-Version: 1.1
Name: ftree
Version: 1.0.2
Summary: Create a File Tree from directory listing.
Home-page: https://pypi.python.org/pypi/ftree
Author: Victor Kindhart
Author-email: digitloft@gmail.com
License: GPL
Platform: UNKNOWN
Classifier: Environment :: Console
Classifier: Programming Language :: Python
